random_face/__init__.py
random_face/demo.py
random_face/engine_base.py
random_face/engine_openvino.py
random_face/functional.py
random_face/random_face.py
random_face/configs/config.json
random_face/configs/model_zoo.json
random_face/data/MappingNetwork.bin
random_face/data/MappingNetwork.xml
random_face/data/SynthesisNetwork.bin
random_face/data/SynthesisNetwork.xml
random_face-2021.7.21.1.dist-info/LICENSE
random_face-2021.7.21.1.dist-info/METADATA
random_face-2021.7.21.1.dist-info/WHEEL
random_face-2021.7.21.1.dist-info/top_level.txt
random_face-2021.7.21.1.dist-info/zip-safe
random_face-2021.7.21.1.dist-info/RECORD
