Metadata-Version: 2.1
Name: random-face
Version: 2021.7.21.1
Summary: Random Face
Home-page: UNKNOWN
Author: Sergei Belousov aka BeS
Author-email: sergei.o.belousov@gmail.com
License: UNKNOWN
Platform: UNKNOWN
Classifier: Programming Language :: Python :: 3
License-File: LICENSE
Requires-Dist: gdown
Requires-Dist: numpy
Requires-Dist: opencv-python
Requires-Dist: openvino
Requires-Dist: jupyter
Requires-Dist: blessed
